bw2qsd/__init__.py
bw2qsd/_cf_getter.py
bw2qsd/_db_downloader.py
bw2qsd/_exceptions.py
bw2qsd/utils.py
bw2qsd/eidl/__init__.py
bw2qsd/eidl/core.py
bw2qsd/eidl/storage.py
bw2qsd-0.1.4.dist-info/LICENSE.txt
bw2qsd-0.1.4.dist-info/METADATA
bw2qsd-0.1.4.dist-info/WHEEL
bw2qsd-0.1.4.dist-info/top_level.txt
bw2qsd-0.1.4.dist-info/RECORD
