Metadata-Version: 2.1
Name: bw2qsd
Version: 0.1.4
Summary: Bridging Brightway2 and QSD packages for LCA
Home-page: https://github.com/QSD-Group/BW2QSD
Author: Yalin Li
Author-email: mailto.yalin.li@gmail.com
License: UIUC
Keywords: quantitative sustainable design,Brightway2,life cycle assessment,database importer
Platform: Windows
Platform: Mac
Platform: Linux
Classifier: License :: OSI Approved :: University of Illinois/NCSA Open Source License
Classifier: Environment :: Console
Classifier: Topic :: Education
Classifier: Topic :: Scientific/Engineering
Classifier: Topic :: Scientific/Engineering :: Chemistry
Classifier: Topic :: Scientific/Engineering :: Mathematics
Classifier: Intended Audience :: Developers
Classifier: Intended Audience :: Education
Classifier: Intended Audience :: Manufacturing
Classifier: Intended Audience :: Science/Research
Classifier: Natural Language :: English
Classifier: Operating System :: OS Independent
Classifier: Programming Language :: Python :: 3.9
Classifier: Programming Language :: Python :: 3.10
License-File: LICENSE.txt
Requires-Dist: brightway2 (==2.4.2)
Requires-Dist: beautifulsoup4
Requires-Dist: py7zr
